djangocms_pai_bootstrap4/__init__.py
djangocms_pai_bootstrap4/apps.py
djangocms_pai_bootstrap4/templates/djangocms_pai_bootstrap4/base.html
djangocms_pai_bootstrap4-0.0.1.dist-info/AUTHORS.rst
djangocms_pai_bootstrap4-0.0.1.dist-info/LICENSE.txt
djangocms_pai_bootstrap4-0.0.1.dist-info/METADATA
djangocms_pai_bootstrap4-0.0.1.dist-info/WHEEL
djangocms_pai_bootstrap4-0.0.1.dist-info/top_level.txt
djangocms_pai_bootstrap4-0.0.1.dist-info/RECORD
